<rules>
  <!--p3c-->
  <rule key="CommentsMustBeJavadocFormatRule">
    <priority>MAJOR</priority>
    <configKey><![CDATA[rulesets/java/ali-comment.xml/CommentsMustBeJavadocFormatRule]]></configKey>
  </rule>
  <rule key="AbstractMethodOrInterfaceMethodMustUseJavadocRule">
    <priority>MAJOR</priority>
    <configKey><![CDATA[rulesets/java/ali-comment.xml/AbstractMethodOrInterfaceMethodMustUseJavadocRule]]></configKey>
  </rule>
  <rule key="ClassMustHaveAuthorRule">
    <priority>MAJOR</priority>
    <configKey><![CDATA[rulesets/java/ali-comment.xml/ClassMustHaveAuthorRule]]></configKey>
  </rule>
  <rule key="EnumConstantsMustHaveCommentRule">
    <priority>CRITICAL</priority>
    <configKey><![CDATA[rulesets/java/ali-comment.xml/EnumConstantsMustHaveCommentRule]]></configKey>
  </rule>
  <rule key="AvoidCommentBehindStatementRule">
    <priority>MAJOR</priority>
    <configKey><![CDATA[rulesets/java/ali-comment.xml/AvoidCommentBehindStatementRule]]></configKey>
  </rule>
  <rule key="RemoveCommentedCodeRule">
    <priority>MAJOR</priority>
    <configKey><![CDATA[rulesets/java/ali-comment.xml/RemoveCommentedCodeRule]]></configKey>
  </rule>

</rules>
